{
  "$comment": "What the stats monitor watches. It NEVER edits site data — it only alerts (via a GitHub issue) when a public source drifts from these baselines, so a human can verify in-app and update. When you confirm and update a real figure on the site, bump its baseline here too.",
  "metrics": [
    {
      "id": "spotify-monthly-listeners",
      "label": "Spotify monthly listeners",
      "sourceName": "kworb.net — Spotify listeners",
      "sourceUrl": "https://kworb.net/spotify/listeners.html",
      "extractor": "kworbListeners",
      "artistId": "3wcj11K77LjEY1PkEazffa",
      "field": "monthlyListeners",
      "kind": "drift",
      "threshold": 0.03,
      "baseline": 53487613,
      "note": "Shown on the site as ~53.49M (app/data/africasBiggest.ts). Re-verify in the Spotify app before updating."
    },
    {
      "id": "spotify-peak-listeners",
      "label": "Spotify peak monthly listeners (all-time high)",
      "sourceName": "kworb.net — Spotify listeners",
      "sourceUrl": "https://kworb.net/spotify/listeners.html",
      "extractor": "kworbListeners",
      "artistId": "3wcj11K77LjEY1PkEazffa",
      "field": "peakListeners",
      "kind": "peak",
      "baseline": 53487613,
      "note": "A new all-time peak is a milestone worth logging on /updates."
    },
    {
      "id": "spotify-listeners-rank",
      "label": "Global rank by Spotify monthly listeners",
      "sourceName": "kworb.net — Spotify listeners",
      "sourceUrl": "https://kworb.net/spotify/listeners.html",
      "extractor": "kworbListeners",
      "artistId": "3wcj11K77LjEY1PkEazffa",
      "field": "rank",
      "kind": "rank",
      "threshold": 5,
      "baseline": 61,
      "note": "Burna Boy's position on kworb's global monthly-listeners ranking (lower is better). A move of 5+ places is worth a look."
    },
    {
      "id": "spotify-total-streams",
      "label": "Total Spotify streams (all songs)",
      "sourceName": "kworb.net — Spotify artist total",
      "sourceUrl": "https://kworb.net/spotify/artist/3wcj11K77LjEY1PkEazffa_songs.html",
      "extractor": "kworbTotalStreams",
      "kind": "drift",
      "threshold": 0.03,
      "baseline": 10297429319,
      "note": "Cumulative Spotify streams across every Burna Boy song — worth a milestone note as it climbs (e.g. crossing 11B)."
    }
  ]
}
